txttk/__init__.py
txttk/corpus.py
txttk/feature.py
txttk/nlptools.py
txttk/report.py
txttk/retools.py
txttk/txttk.py
txttk-0.11.0.dist-info/DESCRIPTION.rst
txttk-0.11.0.dist-info/METADATA
txttk-0.11.0.dist-info/RECORD
txttk-0.11.0.dist-info/WHEEL
txttk-0.11.0.dist-info/metadata.json
txttk-0.11.0.dist-info/top_level.txt
