Metadata-Version: 2.0
Name: txttk
Version: 0.11.0
Summary: Text Toolkit: manipulate text & regular expression
Home-page: https://github.com/jeroyang/txttk
Author: Chia-Jung, Yang
Author-email: jeroyang@gmail.com
License: BSD
Keywords: txttk
Platform: UNKNOWN
Classifier: Development Status :: 4 - Beta
Classifier: Intended Audience :: Developers
Classifier: License :: OSI Approved :: BSD License
Classifier: Natural Language :: English
Classifier: Programming Language :: Python :: 2
Classifier: Programming Language :: Python :: 2.7
Classifier: Programming Language :: Python :: 3
Classifier: Programming Language :: Python :: 3.3
Classifier: Programming Language :: Python :: 3.4
Classifier: Programming Language :: Python :: 3.5
Classifier: Programming Language :: Python :: 3.6
